{
  "retty_id": "100001764707",
  "slug": "cafe-pool-bar-contact-764707",
  "hp_status": "not_generated",
  "last_crawled": "2026-06-03T16:03:33Z",
  "last_owner_update": null,
  "last_built": null,
  "name": "Cafe & Pool Bar Contact",
  "category": "バー",
  "categories": [
    "バー",
    "ダーツバー"
  ],
  "address": "東京都渋谷区恵比寿１-１１-１５ エビスリヨンビル６F",
  "postal_code": "1500013",
  "tel": "03-6455-6871",
  "hours": {
    "mon": {
      "open": "17:00",
      "close": "02:00"
    },
    "tue": {
      "open": "17:00",
      "close": "02:00"
    },
    "wed": {
      "open": "17:00",
      "close": "02:00"
    },
    "thu": {
      "open": "17:00",
      "close": "02:00"
    },
    "holiday": {
      "open": "17:00",
      "close": "02:00"
    },
    "fri": {
      "open": "17:00",
      "close": "03:00"
    },
    "sat": {
      "open": "17:00",
      "close": "03:00"
    }
  },
  "hours_raw": null,
  "budget": {
    "lunch": 1000,
    "dinner": 6000
  },
  "budget_raw": "ランチ予算: 〜1000円 ディナー予算: 〜6000円",
  "geo": {
    "lat": 35.64669796461088,
    "lng": 139.71132856564142
  },
  "retty_url": "https://retty.me/area/PRE13/ARE7/SUB701/100001764707/",
  "retty_photos": [
    "https://ximg.retty.me/crop/s1200x900/-/retty/img_ebisu/restaurant/100001764707/archive/3493203-677cb620c741f.jpg",
    "https://ximg.retty.me/crop/s388x388/q80/das/-/retty/img_ebisu/restaurant/100001764707/archive/3493203-677cb620c741f.jpg",
    "https://ximg.retty.me/crop/s388x388/q80/das/-/retty/img_ebisu/restaurant/100001764707/archive/3493192-677cb60a7c5af.jpg",
    "https://ximg.retty.me/crop/s388x388/q80/das/-/retty/img_ebisu/restaurant/100001764707/archive/3493210-677cb626f00a6.jpg",
    "https://ximg.retty.me/crop/s388x388/q80/das/-/retty/img_ebisu/restaurant/100001764707/archive/3493166-677cb5f2568de.jpg",
    "https://ximg.retty.me/crop/s388x388/q80/das/-/retty/img_ebisu/restaurant/100001764707/archive/3493167-677cb5f3776d7.jpg",
    "https://ximg.retty.me/crop/s388x388/q80/das/-/retty/img_ebisu/restaurant/100001764707/archive/3493211-677cb62852ebd.jpg",
    "https://ximg.retty.me/crop/s388x388/q80/das/-/retty/img_ebisu/restaurant/100001764707/archive/3493177-677cb5fd29db2.jpg",
    "https://ximg.retty.me/crop/s388x388/q80/das/-/retty/img_ebisu/restaurant/100001764707/archive/3493169-677cb5f49cc2c.jpg",
    "https://ximg.retty.me/crop/s388x388/q80/das/-/retty/img_ebisu/restaurant/100001764707/archive/3493212-677cb62926393.jpg",
    "https://ximg.retty.me/crop/s388x388/q80/das/-/retty/img_ebisu/restaurant/100001764707/archive/3493179-677cb5fe42f3a.jpg",
    "https://ximg.retty.me/crop/s388x388/q80/das/-/retty/img_ebisu/restaurant/100001764707/archive/3493170-677cb5f5b2830.jpg",
    "https://ximg.retty.me/crop/s388x388/q80/das/-/retty/img_ebisu/restaurant/100001764707/archive/3493213-677cb62a05ce3.jpg"
  ],
  "retty_rating": null,
  "retty_review_count": null,
  "nearest_station": "恵比寿駅から徒歩1分",
  "payment_accepted": "カード可 : (VISA,MASTERCARD,AMEX,DINERS,JCB)",
  "owner_message": "",
  "owner_photos": [],
  "menu": [
    {
      "dish_slug": "dish-000",
      "name": "※表記は税込価格です。",
      "price": null,
      "price_raw": null,
      "photo_url": null,
      "description": null
    },
    {
      "dish_slug": "dish-001",
      "name": "■ビリヤード料金",
      "price": null,
      "price_raw": null,
      "photo_url": null,
      "description": null
    },
    {
      "dish_slug": "1-002",
      "name": "男性 1時間",
      "price": 700,
      "price_raw": "700円",
      "photo_url": null,
      "description": null
    },
    {
      "dish_slug": "1-003",
      "name": "女性 1時間",
      "price": 500,
      "price_raw": "500円",
      "photo_url": null,
      "description": null
    },
    {
      "dish_slug": "1play-004",
      "name": "男性 1Play",
      "price": 200,
      "price_raw": "200円",
      "photo_url": null,
      "description": null
    },
    {
      "dish_slug": "1play-005",
      "name": "女性 1Play",
      "price": 100,
      "price_raw": "100円",
      "photo_url": null,
      "description": null
    },
    {
      "dish_slug": "night-menu-17-00-006",
      "name": "■NIGHT MENU（おつまみ） 17:00から",
      "price": null,
      "price_raw": null,
      "photo_url": null,
      "description": null
    },
    {
      "dish_slug": "dish-007",
      "name": "ポテトチップス",
      "price": 600,
      "price_raw": "600円",
      "photo_url": null,
      "description": null
    },
    {
      "dish_slug": "dish-008",
      "name": "かわきもの",
      "price": 700,
      "price_raw": "700円",
      "photo_url": null,
      "description": null
    },
    {
      "dish_slug": "dish-009",
      "name": "ビーフジャーキー",
      "price": 750,
      "price_raw": "750円",
      "photo_url": null,
      "description": null
    },
    {
      "dish_slug": "dish-010",
      "name": "ミックスナッツ",
      "price": 800,
      "price_raw": "800円",
      "photo_url": null,
      "description": null
    },
    {
      "dish_slug": "1-5-011",
      "name": "たこ焼き（1皿5個）",
      "price": 850,
      "price_raw": "850円",
      "photo_url": null,
      "description": null
    },
    {
      "dish_slug": "1-3-012",
      "name": "焼きおにぎり（1皿3個）",
      "price": 850,
      "price_raw": "850円",
      "photo_url": null,
      "description": null
    },
    {
      "dish_slug": "dish-013",
      "name": "野菜スティック",
      "price": 900,
      "price_raw": "900円",
      "photo_url": null,
      "description": null
    },
    {
      "dish_slug": "dish-014",
      "name": "コーンバター",
      "price": 850,
      "price_raw": "850円",
      "photo_url": null,
      "description": null
    },
    {
      "dish_slug": "2-015",
      "name": "アメリカンドック（2ヶ）",
      "price": 900,
      "price_raw": "900円",
      "photo_url": null,
      "description": null
    },
    {
      "dish_slug": "2-016",
      "name": "チーズドック（2ヶ）",
      "price": 900,
      "price_raw": "900円",
      "photo_url": null,
      "description": null
    },
    {
      "dish_slug": "dish-017",
      "name": "ポテトもち（チーズ入り）",
      "price": 900,
      "price_raw": "900円",
      "photo_url": null,
      "description": null
    },
    {
      "dish_slug": "dish-018",
      "name": "ポテトもち（カマンベール入り）",
      "price": 900,
      "price_raw": "900円",
      "photo_url": null,
      "description": null
    },
    {
      "dish_slug": "dish-019",
      "name": "野菜かき揚げ",
      "price": 900,
      "price_raw": "900円",
      "photo_url": null,
      "description": null
    },
    {
      "dish_slug": "dish-020",
      "name": "えびと蓮根の落とし揚げ",
      "price": 900,
      "price_raw": "900円",
      "photo_url": null,
      "description": null
    },
    {
      "dish_slug": "dish-021",
      "name": "枝豆ととうもろこしのつまみ揚げ",
      "price": 950,
      "price_raw": "950円",
      "photo_url": null,
      "description": null
    },
    {
      "dish_slug": "dish-022",
      "name": "ミニ春巻",
      "price": 950,
      "price_raw": "950円",
      "photo_url": null,
      "description": null
    },
    {
      "dish_slug": "dish-023",
      "name": "スティック細目春巻",
      "price": 1000,
      "price_raw": "1,000円",
      "photo_url": null,
      "description": null
    },
    {
      "dish_slug": "dish-024",
      "name": "えびチリ",
      "price": 1000,
      "price_raw": "1,000円",
      "photo_url": null,
      "description": null
    },
    {
      "dish_slug": "dish-025",
      "name": "お好み焼（豚玉）",
      "price": 1000,
      "price_raw": "1,000円",
      "photo_url": null,
      "description": null
    },
    {
      "dish_slug": "dish-026",
      "name": "ニラチヂミ",
      "price": 1000,
      "price_raw": "1,000円",
      "photo_url": null,
      "description": null
    },
    {
      "dish_slug": "dish-027",
      "name": "唐揚げ＆ポテトフライ",
      "price": 1200,
      "price_raw": "1,200円",
      "photo_url": null,
      "description": null
    },
    {
      "dish_slug": "dish-028",
      "name": "名古屋名物!! 手羽先唐揚",
      "price": 1200,
      "price_raw": "1,200円",
      "photo_url": null,
      "description": null
    },
    {
      "dish_slug": "dish-029",
      "name": "チキンナゲット＆ポテト",
      "price": 1250,
      "price_raw": "1,250円",
      "photo_url": null,
      "description": null
    },
    {
      "dish_slug": "dish-030",
      "name": "ウィンナーチョリソー",
      "price": 1250,
      "price_raw": "1,250円",
      "photo_url": null,
      "description": null
    },
    {
      "dish_slug": "dish-031",
      "name": "チーズサラミ",
      "price": 1300,
      "price_raw": "1,300円",
      "photo_url": null,
      "description": null
    },
    {
      "dish_slug": "dish-032",
      "name": "チーズの盛り合わせ",
      "price": 1500,
      "price_raw": "1,500円",
      "photo_url": null,
      "description": null
    },
    {
      "dish_slug": "dish-033",
      "name": "クリーミーコロッケ（コーン入り）",
      "price": 1500,
      "price_raw": "1,500円",
      "photo_url": null,
      "description": null
    },
    {
      "dish_slug": "dish-034",
      "name": "ライスコロッケ（チーズ）",
      "price": 1500,
      "price_raw": "1,500円",
      "photo_url": null,
      "description": null
    },
    {
      "dish_slug": "dish-035",
      "name": "尾付きえびフリッター",
      "price": 1550,
      "price_raw": "1,550円",
      "photo_url": null,
      "description": null
    },
    {
      "dish_slug": "dish-036",
      "name": "モッツァレラチーズスティック春巻",
      "price": 1550,
      "price_raw": "1,550円",
      "photo_url": null,
      "description": null
    },
    {
      "dish_slug": "dish-037",
      "name": "完熟トマトソースのピザワッフル",
      "price": 1600,
      "price_raw": "1,600円",
      "photo_url": null,
      "description": null
    },
    {
      "dish_slug": "dish-038",
      "name": "カルボナーラ",
      "price": 1700,
      "price_raw": "1,700円",
      "photo_url": null,
      "description": null
    },
    {
      "dish_slug": "dish-039",
      "name": "たらこと舞茸のスパゲティー",
      "price": 1700,
      "price_raw": "1,700円",
      "photo_url": null,
      "description": null
    },
    {
      "dish_slug": "dish-040",
      "name": "チョコレート盛り合わせ",
      "price": 1800,
      "price_raw": "1,800円",
      "photo_url": null,
      "description": null
    },
    {
      "dish_slug": "dish-041",
      "name": "※表記は税込価格です。",
      "price": null,
      "price_raw": null,
      "photo_url": null,
      "description": null
    },
    {
      "dish_slug": "dish-042",
      "name": "※表記は税込価格です。",
      "price": null,
      "price_raw": null,
      "photo_url": null,
      "description": null
    },
    {
      "dish_slug": "dish-043",
      "name": "■シャンパン",
      "price": null,
      "price_raw": null,
      "photo_url": null,
      "description": null
    },
    {
      "dish_slug": "dish-044",
      "name": "モエ・エ・シャンドン ブリュット",
      "price": 16500,
      "price_raw": "16,500円",
      "photo_url": null,
      "description": null
    },
    {
      "dish_slug": "dish-045",
      "name": "モエ・エ・シャンドン ロゼ",
      "price": 22000,
      "price_raw": "22,000円",
      "photo_url": null,
      "description": null
    },
    {
      "dish_slug": "dish-046",
      "name": "ヴーヴ・クリコ イエローラベル",
      "price": 22000,
      "price_raw": "22,000円",
      "photo_url": null,
      "description": null
    },
    {
      "dish_slug": "dish-047",
      "name": "ヴーヴ・クリコ ロゼ",
      "price": 27500,
      "price_raw": "27,500円",
      "photo_url": null,
      "description": null
    },
    {
      "dish_slug": "dish-048",
      "name": "ヴーヴ・クリコ ドゥミセック",
      "price": 24200,
      "price_raw": "24,200円",
      "photo_url": null,
      "description": null
    },
    {
      "dish_slug": "dish-049",
      "name": "アルマンド ブリニャック ゴールド",
      "price": 132000,
      "price_raw": "132,000円",
      "photo_url": null,
      "description": null
    },
    {
      "dish_slug": "dish-050",
      "name": "キャティア・サファイア",
      "price": 110000,
      "price_raw": "110,000円",
      "photo_url": null,
      "description": null
    },
    {
      "dish_slug": "dish-051",
      "name": "パルメ ブリュット",
      "price": 27500,
      "price_raw": "27,500円",
      "photo_url": null,
      "description": null
    },
    {
      "dish_slug": "dish-052",
      "name": "パルメ ブラン・ド・ブラン",
      "price": 27500,
      "price_raw": "27,500円",
      "photo_url": null,
      "description": null
    },
    {
      "dish_slug": "dish-053",
      "name": "パルメ ロゼ",
      "price": 33000,
      "price_raw": "33,000円",
      "photo_url": null,
      "description": null
    },
    {
      "dish_slug": "dish-054",
      "name": "パルメ グラン・テロワール",
      "price": 55000,
      "price_raw": "55,000円",
      "photo_url": null,
      "description": null
    },
    {
      "dish_slug": "vt2000-055",
      "name": "パルメ VT2000",
      "price": 132000,
      "price_raw": "132,000円",
      "photo_url": null,
      "description": null
    },
    {
      "dish_slug": "dish-056",
      "name": "ドン・ペリニョン ホワイト",
      "price": 110000,
      "price_raw": "110,000円",
      "photo_url": null,
      "description": null
    },
    {
      "dish_slug": "dish-057",
      "name": "ドン・ペリニョン ロゼ",
      "price": 165000,
      "price_raw": "165,000円",
      "photo_url": null,
      "description": null
    },
    {
      "dish_slug": "dish-058",
      "name": "クリュッグ",
      "price": 132000,
      "price_raw": "132,000円",
      "photo_url": null,
      "description": null
    },
    {
      "dish_slug": "xlv-059",
      "name": "XLVキュヴェ ウルトラゼロ",
      "price": 66000,
      "price_raw": "66,000円",
      "photo_url": null,
      "description": null
    },
    {
      "dish_slug": "xlv-060",
      "name": "XLVロゼ リミテッド",
      "price": 154000,
      "price_raw": "154,000円",
      "photo_url": null,
      "description": null
    },
    {
      "dish_slug": "dish-061",
      "name": "ヨシキ ブリュット",
      "price": 55000,
      "price_raw": "55,000円",
      "photo_url": null,
      "description": null
    },
    {
      "dish_slug": "dish-062",
      "name": "ヨシキ ロゼ",
      "price": 88000,
      "price_raw": "88,000円",
      "photo_url": null,
      "description": null
    },
    {
      "dish_slug": "dish-063",
      "name": "ポメリー ブリュット",
      "price": 16500,
      "price_raw": "16,500円",
      "photo_url": null,
      "description": null
    },
    {
      "dish_slug": "dish-064",
      "name": "ポメリー ロゼ",
      "price": 22000,
      "price_raw": "22,000円",
      "photo_url": null,
      "description": null
    },
    {
      "dish_slug": "dish-065",
      "name": "ポメリー ブルースカイ",
      "price": 27500,
      "price_raw": "27,500円",
      "photo_url": null,
      "description": null
    },
    {
      "dish_slug": "dish-066",
      "name": "アンリ・グラン",
      "price": 77000,
      "price_raw": "77,000円",
      "photo_url": null,
      "description": null
    },
    {
      "dish_slug": "dish-067",
      "name": "アンリ・グラン ロゼ",
      "price": 110000,
      "price_raw": "110,000円",
      "photo_url": null,
      "description": null
    },
    {
      "dish_slug": "box-068",
      "name": "アンリ・グラン BOX",
      "price": 99000,
      "price_raw": "99,000円",
      "photo_url": null,
      "description": null
    },
    {
      "dish_slug": "dish-069",
      "name": "クイーン・レア",
      "price": 132000,
      "price_raw": "132,000円",
      "photo_url": null,
      "description": null
    },
    {
      "dish_slug": "dish-070",
      "name": "■スパークリングワイン",
      "price": null,
      "price_raw": null,
      "photo_url": null,
      "description": null
    },
    {
      "dish_slug": "dish-071",
      "name": "カフェ・ド・パリ",
      "price": null,
      "price_raw": null,
      "photo_url": null,
      "description": null
    },
    {
      "dish_slug": "dish-072",
      "name": "・マスカット",
      "price": null,
      "price_raw": null,
      "photo_url": null,
      "description": null
    },
    {
      "dish_slug": "dish-073",
      "name": "・ピーチ",
      "price": null,
      "price_raw": null,
      "photo_url": null,
      "description": null
    },
    {
      "dish_slug": "dish-074",
      "name": "・グレープフルーツ",
      "price": null,
      "price_raw": null,
      "photo_url": null,
      "description": null
    },
    {
      "dish_slug": "dish-075",
      "name": "・サクランボ",
      "price": null,
      "price_raw": null,
      "photo_url": null,
      "description": null
    },
    {
      "dish_slug": "dish-076",
      "name": "・ライチ",
      "price": null,
      "price_raw": null,
      "photo_url": null,
      "description": null
    },
    {
      "dish_slug": "750ml-077",
      "name": "○750mL",
      "price": 5500,
      "price_raw": "5,500円",
      "photo_url": null,
      "description": null
    },
    {
      "dish_slug": "200ml-078",
      "name": "○200mL",
      "price": 2200,
      "price_raw": "2,200円",
      "photo_url": null,
      "description": null
    },
    {
      "dish_slug": "dish-079",
      "name": "■ワイン",
      "price": null,
      "price_raw": null,
      "photo_url": null,
      "description": null
    },
    {
      "dish_slug": "dish-080",
      "name": "○チリ/赤",
      "price": null,
      "price_raw": null,
      "photo_url": null,
      "description": null
    },
    {
      "dish_slug": "dish-081",
      "name": "ロカス・デ・セーニャ",
      "price": 27500,
      "price_raw": "27,500円",
      "photo_url": null,
      "description": null
    },
    {
      "dish_slug": "dish-082",
      "name": "インドミタ サルドス ウルトラ・プレミアム",
      "price": 11000,
      "price_raw": "11,000円",
      "photo_url": null,
      "description": null
    },
    {
      "dish_slug": "dish-083",
      "name": "インドミタ デュエット カベルネ&カルメネール",
      "price": 6600,
      "price_raw": "6,600円",
      "photo_url": null,
      "description": null
    },
    {
      "dish_slug": "dish-084",
      "name": "○チリ/白",
      "price": null,
      "price_raw": null,
      "photo_url": null,
      "description": null
    },
    {
      "dish_slug": "dish-085",
      "name": "インドミタ デュエット シャルドネ",
      "price": 6600,
      "price_raw": "6,600円",
      "photo_url": null,
      "description": null
    },
    {
      "dish_slug": "dish-086",
      "name": "○スペイン/赤",
      "price": null,
      "price_raw": null,
      "photo_url": null,
      "description": null
    },
    {
      "dish_slug": "dish-087",
      "name": "ファウスティーノ ファースト グラン・レセルバ",
      "price": 14300,
      "price_raw": "14,300円",
      "photo_url": null,
      "description": null
    },
    {
      "dish_slug": "dish-088",
      "name": "ファウスティーノ クリアンサ",
      "price": 7700,
      "price_raw": "7,700円",
      "photo_url": null,
      "description": null
    },
    {
      "dish_slug": "dish-089",
      "name": "○スペイン/白",
      "price": null,
      "price_raw": null,
      "photo_url": null,
      "description": null
    },
    {
      "dish_slug": "dish-090",
      "name": "ロサダ ゴデーリョ",
      "price": 11000,
      "price_raw": "11,000円",
      "photo_url": null,
      "description": null
    },
    {
      "dish_slug": "dish-091",
      "name": "ルラ・フェイティセイラ アルバリーニョ",
      "price": 6600,
      "price_raw": "6,600円",
      "photo_url": null,
      "description": null
    },
    {
      "dish_slug": "dish-092",
      "name": "○イタリア/赤",
      "price": null,
      "price_raw": null,
      "photo_url": null,
      "description": null
    },
    {
      "dish_slug": "dish-093",
      "name": "コンチェルト・ディ・フォンテルートリ",
      "price": 27500,
      "price_raw": "27,500円",
      "photo_url": null,
      "description": null
    },
    {
      "dish_slug": "dish-094",
      "name": "バローロ フォンタナフレッダ",
      "price": 16500,
      "price_raw": "16,500円",
      "photo_url": null,
      "description": null
    },
    {
      "dish_slug": "dish-095",
      "name": "ロッソ・ディ・ノートリ・トゥア・リータ",
      "price": 8250,
      "price_raw": "8,250円",
      "photo_url": null,
      "description": null
    },
    {
      "dish_slug": "dish-096",
      "name": "○イタリア/白",
      "price": null,
      "price_raw": null,
      "photo_url": null,
      "description": null
    },
    {
      "dish_slug": "dish-097",
      "name": "テスタマッタ ビアンコ ビービーグラーツ",
      "price": 33000,
      "price_raw": "33,000円",
      "photo_url": null,
      "description": null
    },
    {
      "dish_slug": "dish-098",
      "name": "フェルシナ イ・シストリ",
      "price": 11000,
      "price_raw": "11,000円",
      "photo_url": null,
      "description": null
    },
    {
      "dish_slug": "dish-099",
      "name": "フォンタナフレッダ ガヴィ・ディ・ガヴィ",
      "price": 6600,
      "price_raw": "6,600円",
      "photo_url": null,
      "description": null
    }
  ],
  "featured_menu": [
    {
      "name": "ドン・ペリニョン ロゼ",
      "price": 165000,
      "photo_url": null
    },
    {
      "name": "XLVロゼ リミテッド",
      "price": 154000,
      "photo_url": null
    },
    {
      "name": "アルマンド ブリニャック ゴールド",
      "price": 132000,
      "photo_url": null
    },
    {
      "name": "パルメ VT2000",
      "price": 132000,
      "photo_url": null
    },
    {
      "name": "クリュッグ",
      "price": 132000,
      "photo_url": null
    }
  ],
  "special_info": "",
  "reservation_url": "",
  "sns": {
    "web": "https://cafe-and-poolbar-contact.com/"
  },
  "i18n": {
    "en": {
      "name": "",
      "description": "",
      "featured_menu": []
    },
    "zh": {},
    "ko": {},
    "th": {},
    "vi": {},
    "zh-TW": {}
  },
  "review_url": "https://retty.me/area/PRE13/ARE7/SUB701/100001764707/reports/"
}