{
  "retty_id": "100001699779",
  "slug": "la-nature-node-699779",
  "hp_status": "not_generated",
  "last_crawled": "2026-06-02T17:12:26Z",
  "last_owner_update": null,
  "last_built": null,
  "name": "恵比寿シーシャ LA NATURE NODE",
  "category": "バー",
  "categories": [
    "バー",
    "カフェ"
  ],
  "address": "東京都渋谷区恵比寿西１-７-４ FPG Links EBISU ７F",
  "postal_code": "1500021",
  "tel": "070-3107-7835",
  "hours": {
    "sun": {
      "open": "14:00",
      "close": "29:00"
    },
    "mon": {
      "open": "14:00",
      "close": "29:00"
    },
    "tue": {
      "open": "14:00",
      "close": "29:00"
    },
    "wed": {
      "open": "14:00",
      "close": "29:00"
    },
    "thu": {
      "open": "14:00",
      "close": "29:00"
    },
    "fri": {
      "open": "14:00",
      "close": "29:00"
    },
    "sat": {
      "open": "14:00",
      "close": "29:00"
    },
    "holiday": {
      "open": "14:00",
      "close": "29:00"
    }
  },
  "hours_raw": null,
  "budget": {
    "lunch": 4000,
    "dinner": 6000
  },
  "budget_raw": "ランチ予算: 〜4000円 ディナー予算: 〜6000円",
  "geo": {
    "lat": 35.64785092754981,
    "lng": 139.70891192975358
  },
  "retty_url": "https://retty.me/area/PRE13/ARE7/SUB701/100001699779/",
  "retty_photos": [
    "https://ximg.retty.me/crop/s1200x900/-/retty/img_ebisu/restaurant/100001699779/archive/3598154-6814b4193d99c.jpg",
    "https://ximg.retty.me/crop/s388x388/q80/das/-/retty/img_ebisu/restaurant/100001699779/archive/3598154-6814b4193d99c.jpg",
    "https://ximg.retty.me/crop/s388x388/q80/das/-/retty/img_ebisu/restaurant/100001699779/archive/3598152-6814b40d6e85d.jpg",
    "https://ximg.retty.me/crop/s388x388/q80/das/-/retty/img_ebisu/restaurant/100001699779/archive/3598147-6814b3a25c282.jpg",
    "https://ximg.retty.me/crop/s388x388/q80/das/-/retty/img_ebisu/restaurant/100001699779/archive/3598148-6814b3a6479b2.jpg",
    "https://ximg.retty.me/crop/s388x388/q80/das/-/retty/img_ebisu/restaurant/100001699779/archive/3598144-6814b391b5dae.jpg"
  ],
  "retty_rating": null,
  "retty_review_count": null,
  "nearest_station": null,
  "payment_accepted": "カード可 : (VISA,MASTERCARD,AMEX,JCB)",
  "owner_message": "",
  "owner_photos": [],
  "featured_menu": [],
  "special_info": "",
  "reservation_url": "",
  "sns": {
    "web": "https://lanature-node.com/",
    "instagram": "https://www.instagram.com/lanature_node?igsh=MXVncDd1dDd2bXBqbw==",
    "x": "https://x.com/lanature_node?s=11&t=F8yyvv3ZjjvFPZJ-OH0U3w"
  },
  "i18n": {
    "en": {
      "name": "",
      "description": "",
      "featured_menu": []
    },
    "zh": {},
    "ko": {},
    "th": {},
    "vi": {},
    "zh-TW": {}
  }
}
